STIC/STIC.py
STIC/__init__.py
STIC/canopy_air_stream.py
STIC/closure.py
STIC/constants.py
STIC/diagnostic.py
STIC/initialize_with_solar.py
STIC/initialize_without_solar.py
STIC/iterate_with_solar.py
STIC/iterate_without_solar.py
STIC/net_radiation.py
STIC/root_zone_initialization.py
STIC/root_zone_iteration.py
STIC/soil_moisture_initialization.py
STIC/soil_moisture_iteration.py
STIC/version.txt
STIC/meteorology_conversion/__init__.py
STIC/meteorology_conversion/meteorology_conversion.py
STIC/soil_heat_flux/__init__.py
STIC/soil_heat_flux/calculate_SEBAL_soil_heat_flux.py
STIC/timer/__init__.py
STIC/timer/timer.py
STIC/vegetation_conversion/__init__.py
STIC/vegetation_conversion/vegetation_conversion.py
stic-1.0.4.dist-info/METADATA
stic-1.0.4.dist-info/WHEEL
stic-1.0.4.dist-info/top_level.txt
stic-1.0.4.dist-info/RECORD
