Metadata-Version: 2.4
Name: STIC
Version: 1.0.4
Summary: Surface Temperature Initiated Closure (STIC) Evapotranspiration Model Python Implementation
Author-email: Gregory Halverson <gregory.h.halverson@jpl.nasa.gov>, Kaniska Mallick <kaniska.mallick@list.lu>, Madeleine Pascolini-Campbell <madeleine.a.pascolini-campbell@jpl.nasa.gov>, "Claire S. Villanueva-Weeks" <claire.s.villanueva-weeks@jpl.gov>
Project-URL: Homepage, https://github.com/JPL-Evapotranspiration-Algorithms/STIC
Classifier: Programming Language :: Python :: 3
Classifier: Operating System :: OS Independent
Requires-Python: >=3.10
Requires-Dist: colored-logging
Requires-Dist: ECOv002-CMR
Requires-Dist: ECOv002-granules
Requires-Dist: GEOS5FP>=1.1.1
Requires-Dist: numpy
Requires-Dist: pandas
Requires-Dist: rasters
